{
 "updated": "2026-07-25",
 "files": [
  "automatic-transmission-fluid.json",
  "compressor-oil.json",
  "fuel-additives.json",
  "gasoline-motor-oil.json",
  "hydraulic-oil.json"
 ],
 "count": 83,
 "products": {
  "ATLQT-EA": {
   "path": "/p/amsoil-signature-series-fuel-efficient-100-synthetic-automatic-transmission-fluid-atl/",
   "price": 21.19,
   "rating": null,
   "reviews": 975,
   "name": "AMSOIL Signature Series Fuel-Efficient 100% Synthetic Automatic Transmission Fluid",
   "source": "automatic-transmission-fluid.json"
  },
  "ULVPK-EA": {
   "path": "/p/amsoil-signature-series-ulv-100-synthetic-automatic-transmission-fluid-ulv/",
   "price": 25.89,
   "rating": null,
   "reviews": 975,
   "name": "AMSOIL Signature Series ULV 100% Synthetic Automatic Transmission Fluid ",
   "source": "automatic-transmission-fluid.json"
  },
  "OTFQT-EA": {
   "path": "/p/amsoil-oe-multi-vehicle-100-synthetic-automatic-transmission-fluid-otf/",
   "price": 14.89,
   "rating": null,
   "reviews": 326,
   "name": "AMSOIL OE Multi-Vehicle 100% Synthetic Automatic Transmission Fluid",
   "source": "automatic-transmission-fluid.json"
  },
  "OTLQT-EA": {
   "path": "/p/amsoil-oe-fuel-efficient-100-synthetic-automatic-transmission-fluid-otl/",
   "price": 14.99,
   "rating": null,
   "reviews": 326,
   "name": "AMSOIL OE Fuel-Efficient 100% Synthetic Automatic Transmission Fluid",
   "source": "automatic-transmission-fluid.json"
  },
  "DCTQT-EA": {
   "path": "/p/amsoil-100-synthetic-dct-fluid-dct/",
   "price": 30.79,
   "rating": null,
   "reviews": 33,
   "name": "AMSOIL 100% Synthetic DCT Fluid",
   "source": "automatic-transmission-fluid.json"
  },
  "ATD1G-EA": {
   "path": "/p/amsoil-torque-drive-100-synthetic-automatic-transmission-fluid-atd/",
   "price": 77.29,
   "rating": null,
   "reviews": 45,
   "name": "AMSOIL Torque-Drive® 100% Synthetic Automatic Transmission Fluid",
   "source": "automatic-transmission-fluid.json"
  },
  "ARTQT-EA": {
   "path": "/p/amsoil-super-shift-racing-transmission-fluid-art/",
   "price": 20.39,
   "rating": null,
   "reviews": 25,
   "name": "AMSOIL Super Shift® Racing Transmission Fluid",
   "source": "automatic-transmission-fluid.json"
  },
  "CTG05-EA": {
   "path": "/p/amsoil-sae-10w-100-synthetic-powershift-transmission-fluid-ctg/",
   "price": 324.95,
   "rating": null,
   "reviews": 4,
   "name": "AMSOIL SAE 10W 100% Synthetic Powershift Transmission Fluid",
   "source": "automatic-transmission-fluid.json"
  },
  "CTJ05-EA": {
   "path": "/p/amsoil-sae-30-100-synthetic-powershift-transmission-fluid-ctj/",
   "price": 323.5,
   "rating": null,
   "reviews": 4,
   "name": "AMSOIL SAE 30 100% Synthetic Powershift Transmission Fluid",
   "source": "automatic-transmission-fluid.json"
  },
  "ADBPCN-EA": {
   "path": "/p/amsoil-diesel-4-in-1-fuel-additive-adb/",
   "price": 9.39,
   "rating": 5,
   "reviews": 309,
   "name": "AMSOIL Diesel 4-IN-1 Fuel Additive",
   "source": "fuel-additives.json",
   "variants": {
    "ADBPCN-EA": {
     "price": 9.39,
     "size": "8 oz. Bottle"
    },
    "ADBPCN-CA": {
     "price": 55.35,
     "size": "8 oz. Bottles, Case of 6"
    },
    "ADBHG-EA": {
     "price": 54.29,
     "size": "64 oz. Bottle"
    },
    "ADBHG-CA": {
     "price": 323.7,
     "size": "64 oz. Bottles, Case of 6"
    },
    "ADBCN-EA": {
     "price": 15.39,
     "size": "16 oz. Bottle"
    },
    "ADBCN-CA": {
     "price": 183.3,
     "size": "16 oz. Bottles, Case of 12"
    },
    "ADB55-EA": {
     "price": 4854.75,
     "size": "55 Gallon Drum"
    },
    "ADB05-EA": {
     "price": 497.85,
     "size": "5 Gallon Pail"
    }
   }
  },
  "CVTQT-EA": {
   "path": "/p/amsoil-100-synthetic-cvt-fluid-cvt/",
   "price": 20.39,
   "rating": null,
   "reviews": 217,
   "name": "AMSOIL 100% Synthetic CVT Fluid",
   "source": "automatic-transmission-fluid.json"
  },
  "ATFQT-EA": {
   "path": "/p/amsoil-signature-series-multi-vehicle-100-synthetic-automatic-transmission-fluid-atf/",
   "price": 21.19,
   "rating": null,
   "reviews": 975,
   "name": "AMSOIL Signature Series Multi-Vehicle 100% Synthetic Automatic Transmission Fluid",
   "source": "automatic-transmission-fluid.json"
  },
  "PCH05-EA": {
   "path": "/p/amsoil-iso-32-100-synthetic-compressor-oil-pch/",
   "price": 384.5,
   "rating": 5,
   "reviews": 57,
   "name": "AMSOIL ISO 32 100% Synthetic Compressor Oil",
   "source": "compressor-oil.json"
  },
  "PCJQT-EA": {
   "path": "/p/amsoil-iso-68-100-synthetic-compressor-oil-pcj/",
   "price": 19.89,
   "rating": 5,
   "reviews": 57,
   "name": "AMSOIL ISO 68 100% Synthetic Compressor Oil",
   "source": "compressor-oil.json"
  },
  "PCKQT-EA": {
   "path": "/p/amsoil-iso-100-100-synthetic-compressor-oil-pck/",
   "price": 20.89,
   "rating": 5,
   "reviews": 57,
   "name": "AMSOIL ISO 100 100% Synthetic Compressor Oil",
   "source": "compressor-oil.json"
  },
  "SEI05-EA": {
   "path": "/p/amsoil-sirocco-iso-32-46-compressor-oil-sei/",
   "price": 543.65,
   "rating": 5,
   "reviews": 2,
   "name": "AMSOIL SIROCCO® ISO-32/46 Compressor Oil",
   "source": "compressor-oil.json"
  },
  "PCIQT-EA": {
   "path": "/p/amsoil-iso-46-100-synthetic-compressor-oil-pci/",
   "price": 19.69,
   "rating": null,
   "reviews": 57,
   "name": "AMSOIL ISO 46 100% Synthetic Compressor Oil",
   "source": "compressor-oil.json"
  },
  "AIRBA-EA": {
   "path": "/p/amsoil-100-synthetic-air-tool-oil-airba/",
   "price": 5.59,
   "rating": null,
   "reviews": 8,
   "name": "AMSOIL 100% Synthetic Air Tool Oil",
   "source": "compressor-oil.json"
  },
  "MOBCN-EA": {
   "path": "/p/amsoil-motorcycle-octane-boost-mob/",
   "price": 6.99,
   "rating": 5,
   "reviews": 159,
   "name": "AMSOIL Motorcycle Octane Boost",
   "source": "fuel-additives.json",
   "variants": {
    "MOBCN-EA": {
     "price": 6.99,
     "size": "4 oz. Bottle"
    },
    "MOBCN-CA": {
     "price": 83.1,
     "size": "4 oz. Bottles, Case of 12"
    }
   }
  },
  "ADFPCN-EA": {
   "path": "/p/amsoil-diesel-injector-clean-fuel-additive-adf/",
   "price": 7.49,
   "rating": 5,
   "reviews": 146,
   "name": "AMSOIL Diesel Injector Clean Fuel Additive",
   "source": "fuel-additives.json",
   "variants": {
    "ADFPCN-EA": {
     "price": 7.49,
     "size": "8 oz. Bottle"
    },
    "ADFPCN-CA": {
     "price": 44.15,
     "size": "8 oz. Bottles, Case of 6"
    },
    "ADFHG-EA": {
     "price": 41.19,
     "size": "64 oz. Bottle"
    },
    "ADFHG-CA": {
     "price": 245.05,
     "size": "64 oz. Bottles, Case of 6"
    },
    "ADFCN-EA": {
     "price": 12.09,
     "size": "16 oz. Bottle"
    },
    "ADFCN-CA": {
     "price": 143.1,
     "size": "16 oz. Bottles, Case of 12"
    },
    "ADF55-EA": {
     "price": 3541.05,
     "size": "55 Gallon Drum"
    },
    "ADF05-EA": {
     "price": 368.7,
     "size": "5 Gallon Pail"
    }
   }
  },
  "ACBCN-EA": {
   "path": "/p/amsoil-diesel-cetane-boost-fuel-additive-acb/",
   "price": 13.59,
   "rating": 5,
   "reviews": 112,
   "name": "AMSOIL Diesel Cetane Boost Fuel Additive",
   "source": "fuel-additives.json",
   "variants": {
    "ACBHG-EA": {
     "price": 46.09,
     "size": "64 oz. Bottle"
    },
    "ACBHG-CA": {
     "price": 275,
     "size": "64 oz. Bottles, Case of 6"
    },
    "ACBCN-EA": {
     "price": 13.59,
     "size": "16 oz. Bottle"
    },
    "ACBCN-CA": {
     "price": 161.8,
     "size": "16 oz. Bottles, Case of 12"
    },
    "ACB55-EA": {
     "price": 4084.8,
     "size": "55 Gallon Drum"
    },
    "ACB05-EA": {
     "price": 419.05,
     "size": "5 Gallon Pail"
    }
   }
  },
  "DRCQT-EA": {
   "path": "/p/amsoil-diesel-recovery-fuel-treatment-drc/",
   "price": 18.59,
   "rating": 5,
   "reviews": 8,
   "name": "AMSOIL Diesel Recovery Fuel Treatment",
   "source": "fuel-additives.json",
   "variants": {
    "DRCQT-EA": {
     "price": 18.59,
     "size": "30 oz. Bottle"
    },
    "DRCQT-CA": {
     "price": 221.55,
     "size": "30 oz. Bottles, Case of 12"
    }
   }
  },
  "ADSPCN-EA": {
   "path": "/p/amsoil-diesel-injector-clean-cetane-boost-fuel-additive-ads/",
   "price": 7.89,
   "rating": 5,
   "reviews": 185,
   "name": "AMSOIL Diesel Injector Clean + Cetane Boost Fuel Additive",
   "source": "fuel-additives.json",
   "variants": {
    "ADSPCN-EA": {
     "price": 7.89,
     "size": "8 oz. Bottle"
    },
    "ADSPCN-CA": {
     "price": 46.45,
     "size": "8 oz. Bottles, Case of 6"
    },
    "ADSHG-EA": {
     "price": 61.29,
     "size": "64 oz. Bottle"
    },
    "ADSHG-CA": {
     "price": 366.35,
     "size": "64 oz. Bottles, Case of 6"
    },
    "ADSCN-EA": {
     "price": 18.19,
     "size": "16 oz. Bottle"
    },
    "ADSCN-CA": {
     "price": 216.05,
     "size": "16 oz. Bottles, Case of 12"
    },
    "ADS55-EA": {
     "price": 5260.4,
     "size": "55 Gallon Drum"
    },
    "ADS05-EA": {
     "price": 565.8,
     "size": "5 Gallon Pail"
    }
   }
  },
  "APICN-EA": {
   "path": "/p/amsoil-p-i-performance-improver-gasoline-additive-api/",
   "price": 18.99,
   "rating": 5,
   "reviews": 1167,
   "name": "AMSOIL P.i.® Performance Improver Gasoline Additive",
   "source": "fuel-additives.json"
  },
  "UCLCN-EA": {
   "path": "/p/amsoil-upper-cylinder-lubricant-corrosion-inhibitor-ucl/",
   "price": 7.89,
   "rating": 5,
   "reviews": 381,
   "name": "AMSOIL Upper Cylinder Lubricant Corrosion Inhibitor",
   "source": "fuel-additives.json"
  },
  "AQSQT-EA": {
   "path": "/p/amsoil-quickshot-gasoline-treatment-and-stabilizer-aqs/",
   "price": 13.99,
   "rating": 5,
   "reviews": 353,
   "name": "AMSOIL Quickshot® Gasoline Treatment and Stabilizer",
   "source": "fuel-additives.json"
  },
  "ASTCN-EA": {
   "path": "/p/amsoil-gasoline-stabilizer-ast/",
   "price": 16.59,
   "rating": 5,
   "reviews": 171,
   "name": "AMSOIL Gasoline Stabilizer",
   "source": "fuel-additives.json"
  },
  "AOBBE-EA": {
   "path": "/p/amsoil-dominator-octane-boost-aob/",
   "price": 14.39,
   "rating": 5,
   "reviews": 122,
   "name": "AMSOIL DOMINATOR® Octane Boost",
   "source": "fuel-additives.json"
  },
  "ADDCN-EA": {
   "path": "/p/amsoil-diesel-cold-flow-fuel-additive-add/",
   "price": 12.99,
   "rating": 5,
   "reviews": 309,
   "name": "AMSOIL Diesel Cold Flow Fuel Additive",
   "source": "fuel-additives.json"
  },
  "AZSQT-EA": {
   "path": "/p/amsoil-signature-series-0w-16-100-synthetic-motor-oil-azs/",
   "price": 17.99,
   "rating": 5,
   "reviews": 6985,
   "name": "AMSOIL Signature Series 0W-16 100% Synthetic Motor Oil",
   "source": "gasoline-motor-oil.json"
  },
  "ASMQT-EA": {
   "path": "/p/amsoil-signature-series-0w-20-100-synthetic-motor-oil-asm/",
   "price": 17.99,
   "rating": 5,
   "reviews": 6985,
   "name": "AMSOIL Signature Series 0W-20 100% Synthetic Motor Oil",
   "source": "gasoline-motor-oil.json"
  },
  "AZOQT-EA": {
   "path": "/p/amsoil-signature-series-0w-30-100-synthetic-motor-oil-azo/",
   "price": 21.89,
   "rating": 5,
   "reviews": 6985,
   "name": "AMSOIL Signature Series 0W-30 100% Synthetic Motor Oil",
   "source": "gasoline-motor-oil.json"
  },
  "AZFQT-EA": {
   "path": "/p/amsoil-signature-series-0w-40-100-synthetic-motor-oil-azf/",
   "price": 17.99,
   "rating": 5,
   "reviews": 6985,
   "name": "AMSOIL Signature Series 0W-40 100% Synthetic Motor Oil",
   "source": "gasoline-motor-oil.json"
  },
  "ALMQT-EA": {
   "path": "/p/amsoil-signature-series-5w-20-100-synthetic-motor-oil-alm/",
   "price": 17.99,
   "rating": 5,
   "reviews": 6985,
   "name": "AMSOIL Signature Series 5W-20 100% Synthetic Motor Oil",
   "source": "gasoline-motor-oil.json"
  },
  "ASLQT-EA": {
   "path": "/p/amsoil-signature-series-5w-30-100-synthetic-motor-oil-asl/",
   "price": 17.99,
   "rating": 5,
   "reviews": 6985,
   "name": "AMSOIL Signature Series 5W-30 100% Synthetic Motor Oil",
   "source": "gasoline-motor-oil.json"
  },
  "AMRQT-EA": {
   "path": "/p/amsoil-signature-series-5w-50-100-synthetic-motor-oil-amr/",
   "price": 17.99,
   "rating": 5,
   "reviews": 6985,
   "name": "AMSOIL Signature Series 5W-50 100% Synthetic Motor Oil",
   "source": "gasoline-motor-oil.json"
  },
  "ATMQT-EA": {
   "path": "/p/amsoil-signature-series-10w-30-100-synthetic-motor-oil-atm/",
   "price": 17.99,
   "rating": 5,
   "reviews": 6985,
   "name": "AMSOIL Signature Series 10W-30 100% Synthetic Motor Oil",
   "source": "gasoline-motor-oil.json"
  },
  "XLZQT-EA": {
   "path": "/p/amsoil-extended-life-0w-20-100-synthetic-motor-oil-xlz/",
   "price": 15.49,
   "rating": 5,
   "reviews": 1470,
   "name": "AMSOIL Extended-Life 0W-20 100% Synthetic Motor Oil ",
   "source": "gasoline-motor-oil.json"
  },
  "XLFQT-EA": {
   "path": "/p/amsoil-extended-life-5w-30-100-synthetic-motor-oil-xlf/",
   "price": 15.59,
   "rating": 5,
   "reviews": 1470,
   "name": "AMSOIL Extended-Life 5W-30 100% Synthetic Motor Oil ",
   "source": "gasoline-motor-oil.json"
  },
  "XLTQT-EA": {
   "path": "/p/amsoil-extended-life-10w-30-100-synthetic-motor-oil-xlt/",
   "price": 15.59,
   "rating": 5,
   "reviews": 1470,
   "name": "AMSOIL Extended-Life 10W-30 100% Synthetic Motor Oil ",
   "source": "gasoline-motor-oil.json"
  },
  "XLOQT-EA": {
   "path": "/p/amsoil-extended-life-10w-40-100-synthetic-motor-oil-xlo/",
   "price": 15.59,
   "rating": 5,
   "reviews": 1470,
   "name": "AMSOIL Extended-Life 10W-40 100% Synthetic Motor Oil",
   "source": "gasoline-motor-oil.json"
  },
  "OESQT-EA": {
   "path": "/p/amsoil-oe-0w-16-100-synthetic-motor-oil-oes/",
   "price": 12.59,
   "rating": 5,
   "reviews": 1300,
   "name": "AMSOIL OE 0W-16 100% Synthetic Motor Oil",
   "source": "gasoline-motor-oil.json"
  },
  "OEZQT-EA": {
   "path": "/p/amsoil-oe-0w-20-100-synthetic-motor-oil-oez/",
   "price": 12.59,
   "rating": 5,
   "reviews": 1300,
   "name": "AMSOIL OE 0W-20 100% Synthetic Motor Oil",
   "source": "gasoline-motor-oil.json"
  },
  "OEMQT-EA": {
   "path": "/p/amsoil-oe-5w-20-100-synthetic-motor-oil-oem/",
   "price": 12.59,
   "rating": 5,
   "reviews": 1300,
   "name": "AMSOIL OE 5W-20 100% Synthetic Motor Oil",
   "source": "gasoline-motor-oil.json"
  },
  "OEFQT-EA": {
   "path": "/p/amsoil-oe-5w-30-100-synthetic-motor-oil-oef/",
   "price": 12.59,
   "rating": 5,
   "reviews": 1300,
   "name": "AMSOIL OE 5W-30 100% Synthetic Motor Oil",
   "source": "gasoline-motor-oil.json"
  },
  "OETQT-EA": {
   "path": "/p/amsoil-oe-10w-30-100-synthetic-motor-oil-oet/",
   "price": 12.59,
   "rating": 5,
   "reviews": 1300,
   "name": "AMSOIL OE 10W-30 100% Synthetic Motor Oil",
   "source": "gasoline-motor-oil.json"
  },
  "EZTQT-EA": {
   "path": "/p/amsoil-0w-20-ls-vw-100-synthetic-european-motor-oil-ezt/",
   "price": 17.49,
   "rating": 5,
   "reviews": 819,
   "name": "AMSOIL 0W-20 LS-VW 100% Synthetic European Motor Oil",
   "source": "gasoline-motor-oil.json"
  },
  "EOTQT-EA": {
   "path": "/p/amsoil-0w-30-ms-100-synthetic-european-motor-oil-eot/",
   "price": 17.19,
   "rating": 5,
   "reviews": 819,
   "name": "AMSOIL 0W-30 MS 100% Synthetic European Motor Oil",
   "source": "gasoline-motor-oil.json"
  },
  "AELQT-EA": {
   "path": "/p/amsoil-5w-30-ls-100-synthetic-european-motor-oil-ael/",
   "price": 18.89,
   "rating": 5,
   "reviews": 819,
   "name": "AMSOIL 5W-30 LS 100% Synthetic European Motor Oil",
   "source": "gasoline-motor-oil.json"
  },
  "AFLQT-EA": {
   "path": "/p/amsoil-5w-40-ms-100-synthetic-european-motor-oil-afl/",
   "price": 17.89,
   "rating": 5,
   "reviews": 819,
   "name": "AMSOIL 5W-40 MS 100% Synthetic European Motor Oil",
   "source": "gasoline-motor-oil.json"
  },
  "EFMQT-EA": {
   "path": "/p/amsoil-5w-40-fs-100-synthetic-european-motor-oil-efm/",
   "price": 14.29,
   "rating": 5,
   "reviews": 819,
   "name": "AMSOIL 5W-40 FS 100% Synthetic European Motor Oil",
   "source": "gasoline-motor-oil.json"
  },
  "ETSQT-EA": {
   "path": "/p/amsoil-10w-60-fs-100-synthetic-european-motor-oil-ets/",
   "price": 15.49,
   "rating": 5,
   "reviews": 819,
   "name": "AMSOIL 10W-60 FS 100% Synthetic European Motor Oil",
   "source": "gasoline-motor-oil.json"
  },
  "HM020QT-EA": {
   "path": "/p/amsoil-0w-20-100-synthetic-high-mileage-motor-oil-hm020/",
   "price": 14.39,
   "rating": 5,
   "reviews": 411,
   "name": "AMSOIL 0W-20 100% Synthetic High-Mileage Motor Oil",
   "source": "gasoline-motor-oil.json"
  },
  "HM520QT-EA": {
   "path": "/p/amsoil-5w-20-100-synthetic-high-mileage-motor-oil-hm520/",
   "price": 14.49,
   "rating": 5,
   "reviews": 411,
   "name": "AMSOIL 5W-20 100% Synthetic High-Mileage Motor Oil",
   "source": "gasoline-motor-oil.json"
  },
  "HM530QT-EA": {
   "path": "/p/amsoil-5w-30-100-synthetic-high-mileage-motor-oil-hm530/",
   "price": 14.49,
   "rating": 5,
   "reviews": 411,
   "name": "AMSOIL 5W-30 100% Synthetic High-Mileage Motor Oil",
   "source": "gasoline-motor-oil.json"
  },
  "HM1030QT-EA": {
   "path": "/p/amsoil-10w-30-100-synthetic-high-mileage-motor-oil-hm1030/",
   "price": 14.49,
   "rating": 5,
   "reviews": 411,
   "name": "AMSOIL 10W-30 100% Synthetic High-Mileage Motor Oil",
   "source": "gasoline-motor-oil.json"
  },
  "HE016QT-EA": {
   "path": "/p/amsoil-0w-16-100-synthetic-hybrid-motor-oil-he016/",
   "price": 14.39,
   "rating": 5,
   "reviews": 56,
   "name": "AMSOIL 0W-16 100% Synthetic Hybrid Motor Oil",
   "source": "gasoline-motor-oil.json"
  },
  "HE020QT-EA": {
   "path": "/p/amsoil-0w-20-100-synthetic-hybrid-motor-oil-he020/",
   "price": 14.39,
   "rating": 5,
   "reviews": 56,
   "name": "AMSOIL 0W-20 100% Synthetic Hybrid Motor Oil",
   "source": "gasoline-motor-oil.json"
  },
  "ZRTQT-EA": {
   "path": "/p/amsoil-z-rod-10w-30-100-synthetic-motor-oil-zrt/",
   "price": 17.69,
   "rating": 5,
   "reviews": 77,
   "name": "AMSOIL Z-ROD® 10W-30 100% Synthetic Motor Oil",
   "source": "gasoline-motor-oil.json"
  },
  "ZRDQT-EA": {
   "path": "/p/amsoil-z-rod-10w-40-100-synthetic-motor-oil-zrd/",
   "price": 17.69,
   "rating": 5,
   "reviews": 77,
   "name": "AMSOIL Z-ROD® 10W-40 100% Synthetic Motor Oil",
   "source": "gasoline-motor-oil.json"
  },
  "RD20QT-EA": {
   "path": "/p/amsoil-dominator-5w-20-100-synthetic-racing-oil-rd20/",
   "price": 21.09,
   "rating": 5,
   "reviews": 91,
   "name": "AMSOIL DOMINATOR® 5W-20 100% Synthetic Racing Oil",
   "source": "gasoline-motor-oil.json"
  },
  "RD30QT-EA": {
   "path": "/p/amsoil-dominator-10w-30-100-synthetic-racing-oil-rd30/",
   "price": 20.39,
   "rating": 5,
   "reviews": 91,
   "name": "AMSOIL DOMINATOR® 10W-30 100% Synthetic Racing Oil",
   "source": "gasoline-motor-oil.json"
  },
  "RD40QT-EA": {
   "path": "/p/amsoil-dominator-10w-40-100-synthetic-racing-oil-rd40/",
   "price": 20.39,
   "rating": 5,
   "reviews": 91,
   "name": "AMSOIL DOMINATOR® 10W-40 100% Synthetic Racing Oil",
   "source": "gasoline-motor-oil.json"
  },
  "RD50QT-EA": {
   "path": "/p/amsoil-dominator-15w-50-100-synthetic-racing-oil-rd50/",
   "price": 21.19,
   "rating": 5,
   "reviews": 91,
   "name": "AMSOIL DOMINATOR® 15W-50 100% Synthetic Racing Oil",
   "source": "gasoline-motor-oil.json"
  },
  "RD60QT-EA": {
   "path": "/p/amsoil-dominator-sae-60-100-synthetic-racing-oil-rd60/",
   "price": 21.79,
   "rating": 5,
   "reviews": 91,
   "name": "AMSOIL DOMINATOR® SAE 60 100% Synthetic Racing Oil",
   "source": "gasoline-motor-oil.json"
  },
  "AMOQT-EA": {
   "path": "/p/amsoil-premium-protection-10w-40-100-synthetic-motor-oil-amo/",
   "price": 17.89,
   "rating": 5,
   "reviews": 148,
   "name": "AMSOIL Premium Protection 10W-40 100% Synthetic Motor Oil",
   "source": "gasoline-motor-oil.json"
  },
  "AROQT-EA": {
   "path": "/p/amsoil-premium-protection-20w-50-100-synthetic-motor-oil-aro/",
   "price": 18.49,
   "rating": 5,
   "reviews": 148,
   "name": "AMSOIL Premium Protection 20W-50 100% Synthetic Motor Oil",
   "source": "gasoline-motor-oil.json"
  },
  "BRKQT-EA": {
   "path": "/p/amsoil-sae-30-break-in-oil-brk/",
   "price": 14.39,
   "rating": 5,
   "reviews": 77,
   "name": "AMSOIL SAE 30 Break-In Oil",
   "source": "gasoline-motor-oil.json"
  },
  "SB020QT-EA": {
   "path": "/p/amsoil-0w-20-synthetic-blend-motor-oil-sb020/",
   "price": 10.49,
   "rating": 5,
   "reviews": 10,
   "name": "AMSOIL 0W-20 Synthetic-Blend Motor Oil ",
   "source": "gasoline-motor-oil.json"
  },
  "SB520QT-EA": {
   "path": "/p/amsoil-5w-20-synthetic-blend-motor-oil-sb520/",
   "price": 10.59,
   "rating": 5,
   "reviews": 10,
   "name": "AMSOIL 5W-20 Synthetic-Blend Motor Oil ",
   "source": "gasoline-motor-oil.json"
  },
  "SB530QT-EA": {
   "path": "/p/amsoil-5w-30-synthetic-blend-motor-oil-sb530/",
   "price": 10.59,
   "rating": 5,
   "reviews": 10,
   "name": "AMSOIL 5W-30 Synthetic-Blend Motor Oil ",
   "source": "gasoline-motor-oil.json"
  },
  "AWG05-EA": {
   "path": "/p/amsoil-iso-22-100-synthetic-anti-wear-hydraulic-oil-awg/",
   "price": 371.7,
   "rating": 5,
   "reviews": 2,
   "name": "AMSOIL ISO 22 100% Synthetic Anti-Wear Hydraulic Oil",
   "source": "hydraulic-oil.json"
  },
  "AWH05-EA": {
   "path": "/p/amsoil-iso-32-100-synthetic-anti-wear-hydraulic-oil-awh/",
   "price": 348,
   "rating": 5,
   "reviews": 2,
   "name": "AMSOIL ISO 32 100% Synthetic Anti-Wear Hydraulic Oil",
   "source": "hydraulic-oil.json"
  },
  "AWI05-EA": {
   "path": "/p/amsoil-iso-46-100-synthetic-anti-wear-hydraulic-oil-awi/",
   "price": 346.25,
   "rating": 5,
   "reviews": 2,
   "name": "AMSOIL ISO 46 100% Synthetic Anti-Wear Hydraulic Oil",
   "source": "hydraulic-oil.json"
  },
  "HVH05-EA": {
   "path": "/p/amsoil-iso-32-100-synthetic-multi-viscosity-hydraulic-oil-hvh/",
   "price": 282.2,
   "rating": 5,
   "reviews": 4,
   "name": "AMSOIL ISO 32 100% Synthetic Multi-Viscosity Hydraulic Oil",
   "source": "hydraulic-oil.json"
  },
  "HVI05-EA": {
   "path": "/p/amsoil-iso-46-100-synthetic-multi-viscosity-hydraulic-oil-hvi/",
   "price": 271.45,
   "rating": 5,
   "reviews": 4,
   "name": "AMSOIL ISO 46 100% Synthetic Multi-Viscosity Hydraulic Oil",
   "source": "hydraulic-oil.json"
  },
  "HCG32TP-EA": {
   "path": "/p/amsoil-iso-32-commercial-grade-hydraulic-oil-hcg32/",
   "price": 93.2,
   "rating": null,
   "reviews": null,
   "name": "AMSOIL ISO 32 Commercial-Grade Hydraulic Oil",
   "source": "hydraulic-oil.json"
  },
  "HCG46TP-EA": {
   "path": "/p/amsoil-iso-46-commercial-grade-hydraulic-oil-hcg46/",
   "price": 93.2,
   "rating": null,
   "reviews": null,
   "name": "AMSOIL ISO 46 Commercial-Grade Hydraulic Oil",
   "source": "hydraulic-oil.json"
  },
  "HCG68TP-EA": {
   "path": "/p/amsoil-iso-68-commercial-grade-hydraulic-oil-hcg68/",
   "price": 93.25,
   "rating": null,
   "reviews": null,
   "name": "AMSOIL ISO 68 Commercial-Grade Hydraulic Oil",
   "source": "hydraulic-oil.json"
  },
  "BHO05-EA": {
   "path": "/p/amsoil-iso-46-100-synthetic-biodegradable-hydraulic-oil-bho/",
   "price": 407.4,
   "rating": null,
   "reviews": null,
   "name": "AMSOIL ISO 46 100% Synthetic Biodegradable Hydraulic Oil",
   "source": "hydraulic-oil.json"
  },
  "ATHQT-EA": {
   "path": "/p/amsoil-5w-30-100-synthetic-tractor-hydraulic-transmission-oil-ath/",
   "price": 17.49,
   "rating": 5,
   "reviews": 50,
   "name": "AMSOIL 5W-30 100% Synthetic Tractor Hydraulic/Transmission Oil",
   "source": "hydraulic-oil.json"
  },
  "HVG05-EA": {
   "path": "/p/amsoil-iso-22-100-synthetic-multi-viscosity-hydraulic-oil-hvg/",
   "price": 274.75,
   "rating": null,
   "reviews": null,
   "name": "AMSOIL ISO 22 100% Synthetic Multi-Viscosity Hydraulic Oil",
   "source": "hydraulic-oil.json"
  },
  "HVJ05-EA": {
   "path": "/p/amsoil-iso-68-100-synthetic-multi-viscosity-hydraulic-oil-hvj/",
   "price": 293.25,
   "rating": null,
   "reviews": null,
   "name": "AMSOIL ISO 68 100% Synthetic Multi-Viscosity Hydraulic Oil",
   "source": "hydraulic-oil.json"
  }
 }
}
